setup.py
FerrisNose.egg-info/PKG-INFO
FerrisNose.egg-info/SOURCES.txt
FerrisNose.egg-info/dependency_links.txt
FerrisNose.egg-info/entry_points.txt
FerrisNose.egg-info/requires.txt
FerrisNose.egg-info/top_level.txt
ferrisnose/__init__.py
ferrisnose/plugin.py
ferrisnose/testbed.py
ferrisnose/utilities.py