Metadata-Version: 1.1
Name: FerrisNose
Version: 2.1.2
Summary: Nose plugin for testing Google App Engine application. Designed for the Ferris Framework but should work for any App Engine app.
Home-page: https://bitbucket.org/jonparrott/ferrisnose
Author: Jon Parrott
Author-email: jjramone13@gmail.com
License: Apache License 2.0
Platform: UNKNOWN
Classifier: Development Status :: 4 - Beta
Classifier: License :: OSI Approved :: Apache Software License
Classifier: Programming Language :: Python
